trajdl-0.1.0.dist-info/RECORD
trajdl-0.1.0.dist-info/METADATA
trajdl-0.1.0.dist-info/WHEEL
trajdl-0.1.0.dist-info/licenses/LICENSE
trajdl/trajdl_cpp.cpython-312-x86_64-linux-gnu.so
trajdl/config.py
trajdl/__init__.py
trajdl/grid/hierarchy.py
trajdl/grid/base.py
trajdl/grid/__init__.py
trajdl/loss/sampled_softmax.py
trajdl/loss/__init__.py
trajdl/algorithms/ctle.py
trajdl/algorithms/tuler.py
trajdl/algorithms/gmvsae.py
trajdl/algorithms/hier.py
trajdl/algorithms/t2vec.py
trajdl/algorithms/abstract.py
trajdl/algorithms/__init__.py
trajdl/algorithms/loc_pred/stlstm.py
trajdl/algorithms/loc_pred/rnn.py
trajdl/algorithms/loc_pred/__init__.py
trajdl/algorithms/framework/__init__.py
trajdl/algorithms/embeddings/ctle.py
trajdl/algorithms/embeddings/base.py
trajdl/algorithms/embeddings/__init__.py
trajdl/metrics/tul.py
trajdl/metrics/__init__.py
trajdl/metrics/acc.py
trajdl/tokenizers/t2vec.py
trajdl/tokenizers/abstract.py
trajdl/tokenizers/__init__.py
trajdl/tokenizers/locseq.py
trajdl/tokenizers/simple.py
trajdl/tokenizers/slot/__init__.py
trajdl/common/samples.py
trajdl/common/enum.py
trajdl/common/__init__.py
trajdl/utils/traj.py
trajdl/utils/__init__.py
trajdl/datasets/__init__.py
trajdl/datasets/sampler/t2vec.py
trajdl/datasets/sampler/session.py
trajdl/datasets/sampler/__init__.py
trajdl/datasets/sampler/bucket.py
trajdl/datasets/arrow/traj.py
trajdl/datasets/arrow/abstract.py
trajdl/datasets/arrow/schema.py
trajdl/datasets/arrow/__init__.py
trajdl/datasets/arrow/locseq.py
trajdl/datasets/arrow/ext/t2vec.py
trajdl/datasets/arrow/ext/__init__.py
trajdl/datasets/modules/ctle.py
trajdl/datasets/modules/stlstm.py
trajdl/datasets/modules/tuler.py
trajdl/datasets/modules/gmvsae.py
trajdl/datasets/modules/hier.py
trajdl/datasets/modules/t2vec.py
trajdl/datasets/modules/abstract.py
trajdl/datasets/modules/__init__.py
trajdl/datasets/open_source/utils.py
trajdl/datasets/open_source/__init__.py
trajdl/datasets/open_source/hasher.py
trajdl/datasets/open_source/conf.py
trajdl/datasets/base/traj.py
trajdl/datasets/base/abstract.py
