Metadata-Version: 2.1
Name: trajdl
Version: 0.1.0
Summary: A python toolbox for Trajectory Deep Learning.
Author-Email: Chao Song <davidchaosong@outlook.com>, Chaoqun Feng <fengchaoqun.fcq@gmail.com>
Maintainer-Email: Chao Song <davidchaosong@outlook.com>, Chaoqun Feng <fengchaoqun.fcq@gmail.com>
License:                                  Apache License
Classifier: Development Status :: 5 - Production/Stable
Classifier: Programming Language :: C++
Classifier: Programming Language :: Python :: 3.10
Classifier: Programming Language :: Python :: 3.11
Classifier: Programming Language :: Python :: 3.12
Classifier: License :: OSI Approved :: Apache Software License
Classifier: Operating System :: POSIX :: Linux
Classifier: Topic :: Scientific/Engineering :: Artificial Intelligence
Classifier: Topic :: Software Development :: Libraries :: Python Modules
Classifier: Intended Audience :: Developers
Classifier: Intended Audience :: Science/Research
Classifier: Natural Language :: Chinese (Simplified)
Project-URL: Homepage, https://github.com/Spatial-Temporal-Data-Mining/TrajDL
Project-URL: Documentation, https://trajdl.readthedocs.io/en/latest/
Project-URL: Bug tracker, https://github.com/Spatial-Temporal-Data-Mining/TrajDL/issues
Project-URL: Discussions, https://github.com/Spatial-Temporal-Data-Mining/TrajDL/discussions
Project-URL: Changelog, https://github.com/Spatial-Temporal-Data-Mining/TrajDL/blob/master/CHANGELOG.md
Requires-Python: <3.13,>=3.10
Requires-Dist: scikit-learn>=1.3.2
Requires-Dist: gensim==4.3.3
Requires-Dist: polars>=1.17.1
Requires-Dist: orjson>=3.10.6
Requires-Dist: joblib>=1.4.0
Requires-Dist: tqdm>=4.66.4
Requires-Dist: lightning[extra]>=2.3.3
Requires-Dist: pyarrow>=17.0.0
Requires-Dist: torch_tb_profiler>=0.4.3
Requires-Dist: tensorboard>=2.14.0
Requires-Dist: rtree>=1.3.0
Requires-Dist: requests>=2.31.0
Requires-Dist: mmh3>=5.0.1
Requires-Dist: numpy<2.0.0,>=1.24.0
Requires-Dist: pybind11==2.13.1; extra == "dev"
Requires-Dist: pytest>=8.3.2; extra == "dev"
Requires-Dist: pytest-cov>=5.0.0; extra == "dev"
Requires-Dist: build>=1.2.1; extra == "dev"
Requires-Dist: isort==5.13.2; extra == "dev"
Requires-Dist: black[jupyter]==24.8.0; extra == "dev"
Requires-Dist: autoflake==2.3.1; extra == "dev"
Requires-Dist: requests-mock==1.12.1; extra == "dev"
Requires-Dist: mypy>=1.13.0; extra == "dev"
Requires-Dist: jupyter>=1.1.1; extra == "docs"
Requires-Dist: jupytext>=1.16.4; extra == "docs"
Requires-Dist: jupyterlab_myst>=2.4.2; extra == "docs"
Requires-Dist: ipywidgets>=8.1.5; extra == "docs"
Requires-Dist: recommonmark>=0.7.1; extra == "docs"
Requires-Dist: furo>=2024.8.6; extra == "docs"
Requires-Dist: sphinx>=8.0.2; extra == "docs"
Requires-Dist: sphinx-markdown-tables>=0.0.17; extra == "docs"
Requires-Dist: myst-nb>=1.1.2; extra == "docs"
Requires-Dist: sphinx-design>=0.6.1; extra == "docs"
Requires-Dist: sphinx-book-theme>=1.1.3; extra == "docs"
Requires-Dist: sphinx-copybutton>=0.5.2; extra == "docs"
Requires-Dist: toml>=0.10.2; extra == "docs"
Provides-Extra: dev
Provides-Extra: docs
